nbenv/__init__.py
nbenv/cli.py
nbenv/hooks.py
nbenv/nbenv.py
nbenv-0.1.4.dist-info/DESCRIPTION.rst
nbenv-0.1.4.dist-info/METADATA
nbenv-0.1.4.dist-info/RECORD
nbenv-0.1.4.dist-info/WHEEL
nbenv-0.1.4.dist-info/entry_points.txt
nbenv-0.1.4.dist-info/metadata.json
nbenv-0.1.4.dist-info/top_level.txt
