Metadata-Version: 2.0
Name: nbenv
Version: 0.1.4
Summary: Store conda environment package list inside Notebook documents
Home-page: https://github.com/zonca/nbenv
Author: Andrea Zonca
Author-email: code@andreazonca.com
License: MIT license
Keywords: nbenv
Platform: UNKNOWN
Classifier: Development Status :: 2 - Pre-Alpha
Classifier: Intended Audience :: Developers
Classifier: License :: OSI Approved :: MIT License
Classifier: Natural Language :: English
Classifier: Programming Language :: Python :: 2
Classifier: Programming Language :: Python :: 2.7
Classifier: Programming Language :: Python :: 3
Classifier: Programming Language :: Python :: 3.3
Classifier: Programming Language :: Python :: 3.4
Classifier: Programming Language :: Python :: 3.5
Requires-Dist: nbformat
Requires-Dist: jupyter-client
